router_log_preprocessor/__init__.py
router_log_preprocessor/__main__.py
router_log_preprocessor/domain/__init__.py
router_log_preprocessor/domain/_dnsmasq_dhcp.py
router_log_preprocessor/domain/_message.py
router_log_preprocessor/domain/_wlc.py
router_log_preprocessor/hooks/__init__.py
router_log_preprocessor/hooks/abc.py
router_log_preprocessor/hooks/zabbix/__init__.py
router_log_preprocessor/hooks/zabbix/_known_clients.py
router_log_preprocessor/hooks/zabbix/_mapper.py
router_log_preprocessor/hooks/zabbix/_trapper.py
router_log_preprocessor/log_server/__init__.py
router_log_preprocessor/log_server/handler.py
router_log_preprocessor/log_server/server.py
router_log_preprocessor/preprocessors/__init__.py
router_log_preprocessor/preprocessors/dnsmasq_dhcp.py
router_log_preprocessor/preprocessors/typing.py
router_log_preprocessor/preprocessors/wlc.py
router_log_preprocessor/settings.py
router_log_preprocessor/util/__init__.py
router_log_preprocessor/util/logging.py
router_log_preprocessor/util/rfc3164_parser.py
router_log_preprocessor-0.2.0.dist-info/WHEEL
router_log_preprocessor-0.2.0.dist-info/METADATA
router_log_preprocessor-0.2.0.dist-info/LICENSE
router_log_preprocessor-0.2.0.dist-info/entry_points.txt
router_log_preprocessor-0.2.0.dist-info/RECORD
