Metadata-Version: 2.1
Name: router-log-preprocessor
Version: 0.2.0
Summary: 
Home-page: https://github.com/mastdi/router-log-preprocessor
License: Apache-2.0
Author: Martin Storgaard Dieu
Author-email: martin@storgaarddieu.com
Requires-Python: >=3.8,<4.0
Classifier: License :: OSI Approved :: Apache Software License
Classifier: Programming Language :: Python :: 3
Classifier: Programming Language :: Python :: 3.8
Classifier: Programming Language :: Python :: 3.9
Classifier: Programming Language :: Python :: 3.10
Classifier: Programming Language :: Python :: 3.11
Requires-Dist: anyio (>=4.3.0,<5.0.0)
Requires-Dist: asyncio-zabbix-sender (>=0.2.0,<0.3.0)
Requires-Dist: macaddress (>=2.0.2,<3.0.0)
Requires-Dist: pydantic-settings (>=2.2.1,<3.0.0)
Requires-Dist: pydantic[dotenv] (>=2.6.3,<3.0.0)
Project-URL: Repository, https://github.com/mastdi/router-log-preprocessor
